src/__init__.py
src/__main__.py
src/spotipylist.py
src/utils/__init__.py
src/utils/playlist.py
src/utils/playlist_generator.py
spotipylist-0.2.1.dist-info/LICENSE
spotipylist-0.2.1.dist-info/METADATA
spotipylist-0.2.1.dist-info/WHEEL
spotipylist-0.2.1.dist-info/entry_points.txt
spotipylist-0.2.1.dist-info/top_level.txt
spotipylist-0.2.1.dist-info/RECORD
