Metadata-Version: 2.1
Name: spotipylist
Version: 0.2.1
Summary: A playlist generator for creating local playlists using Spotify curated playlists
Home-page: https://github.com/zacharyeller13/spotipylist
Author: Zachary Eller
Author-email: zacharyeller@pm.me
License: MIT License
Project-URL: Bug Tracker, https://github.com/zacharyeller13/spotipylist/issues
Classifier: Development Status :: 3 - Alpha
Classifier: Intended Audience :: Developers
Classifier: Programming Language :: Python :: 3
Classifier: Programming Language :: Python :: 3.6
Classifier: Programming Language :: Python :: 3.7
Classifier: Programming Language :: Python :: 3.8
Classifier: Programming Language :: Python :: 3.9
Classifier: Programming Language :: Python :: 3.10
Classifier: License :: OSI Approved :: MIT License
Requires-Python: >=3.6
License-File: LICENSE
Requires-Dist: spotipy (>=2.19.0)
Requires-Dist: rapidfuzz (>=1.7.1)
